odoo/addons/crm_project_task/README.rst
odoo/addons/crm_project_task/__init__.py
odoo/addons/crm_project_task/__manifest__.py
odoo/addons/crm_project_task/demo/crm_demo.xml
odoo/addons/crm_project_task/i18n/crm_project_task.pot
odoo/addons/crm_project_task/i18n/es.po
odoo/addons/crm_project_task/i18n/fr.po
odoo/addons/crm_project_task/i18n/it.po
odoo/addons/crm_project_task/models/__init__.py
odoo/addons/crm_project_task/models/crm_lead.py
odoo/addons/crm_project_task/models/project_task.py
odoo/addons/crm_project_task/models/res_company.py
odoo/addons/crm_project_task/models/res_config_settings.py
odoo/addons/crm_project_task/readme/CONFIGURE.md
odoo/addons/crm_project_task/readme/CONTRIBUTORS.md
odoo/addons/crm_project_task/readme/DESCRIPTION.md
odoo/addons/crm_project_task/readme/USAGE.md
odoo/addons/crm_project_task/security/ir.model.access.csv
odoo/addons/crm_project_task/static/description/icon.png
odoo/addons/crm_project_task/static/description/index.html
odoo/addons/crm_project_task/tests/__init__.py
odoo/addons/crm_project_task/tests/test_crm_project_task.py
odoo/addons/crm_project_task/views/crm_lead.xml
odoo/addons/crm_project_task/views/project_task.xml
odoo/addons/crm_project_task/views/res_config_settings.xml
odoo/addons/crm_project_task/wizards/__init__.py
odoo/addons/crm_project_task/wizards/crm_create_task.py
odoo/addons/crm_project_task/wizards/crm_create_task.xml
odoo_addon_crm_project_task-18.0.1.0.0.2.dist-info/METADATA
odoo_addon_crm_project_task-18.0.1.0.0.2.dist-info/WHEEL
odoo_addon_crm_project_task-18.0.1.0.0.2.dist-info/top_level.txt
odoo_addon_crm_project_task-18.0.1.0.0.2.dist-info/RECORD
